avahi_summarize/__init__.py
avahi_summarize/main.py
avahi_summarize-0.1.dist-info/METADATA
avahi_summarize-0.1.dist-info/WHEEL
avahi_summarize-0.1.dist-info/top_level.txt
avahi_summarize-0.1.dist-info/RECORD
