Metadata-Version: 2.1
Name: avahi-summarize
Version: 0.1
Summary: Summarizes an article with the use of aws bedrock model claude 3 Sonnet
Requires-Dist: boto3
